{
  "recentFiles": [
    {
      "basename": "README",
      "path": "README.md"
    },
    {
      "basename": "卡片笔记写作法：如何实现从阅读到写作-申克·阿伦斯",
      "path": "pages/400 - RESOURCE/书影音笔记/微信读书同步/文学/卡片笔记写作法：如何实现从阅读到写作-申克·阿伦斯.md"
    },
    {
      "basename": "置身事内：中国政府与经济发展-兰小欢",
      "path": "pages/400 - RESOURCE/书影音笔记/微信读书同步/经济理财/置身事内：中国政府与经济发展-兰小欢.md"
    },
    {
      "basename": "微信读书同步模板",
      "path": "templates/微信读书同步模板.md"
    },
    {
      "basename": "学会提问（原书第12版）-尼尔·布朗 斯图尔特·基利",
      "path": "pages/400 - RESOURCE/书影音笔记/微信读书同步/心理/学会提问（原书第12版）-尼尔·布朗 斯图尔特·基利.md"
    },
    {
      "basename": "认知觉醒：开启自我改变的原动力-周岭",
      "path": "pages/400 - RESOURCE/书影音笔记/微信读书同步/心理/认知觉醒：开启自我改变的原动力-周岭.md"
    },
    {
      "basename": "微信读书清单",
      "path": "pages/400 - RESOURCE/书影音笔记/微信读书同步/微信读书清单.md"
    },
    {
      "basename": "我所理解的生活-韩寒",
      "path": "pages/400 - RESOURCE/书影音笔记/微信读书同步/文学/我所理解的生活-韩寒.md"
    },
    {
      "basename": "世界因你不同：李开复自传（纪念版）-李开复 范海涛",
      "path": "pages/400 - RESOURCE/书影音笔记/微信读书同步/人物传记/世界因你不同：李开复自传（纪念版）-李开复 范海涛.md"
    },
    {
      "basename": "同名同姓受害者协会-下村敦史",
      "path": "pages/400 - RESOURCE/书影音笔记/微信读书同步/精品小说/同名同姓受害者协会-下村敦史.md"
    },
    {
      "basename": "古龙作品大全集（72册）-古龙",
      "path": "pages/400 - RESOURCE/书影音笔记/微信读书同步/精品小说/古龙作品大全集（72册）-古龙.md"
    },
    {
      "basename": "1988：我想和这个世界谈谈-韩寒",
      "path": "pages/400 - RESOURCE/书影音笔记/微信读书同步/精品小说/1988：我想和这个世界谈谈-韩寒.md"
    },
    {
      "basename": "学会提问（原书第11版）-尼尔·布朗 斯图尔特·基利",
      "path": "pages/400 - RESOURCE/书影音笔记/微信读书同步/个人成长/学会提问（原书第11版）-尼尔·布朗 斯图尔特·基利.md"
    },
    {
      "basename": "刻意练习：如何从新手到大师-安德斯·艾利克森 罗伯特·普尔(Robe",
      "path": "pages/400 - RESOURCE/书影音笔记/微信读书同步/个人成长/刻意练习：如何从新手到大师-安德斯·艾利克森 罗伯特·普尔(Robe.md"
    },
    {
      "basename": "obsidian 是可以用一辈子不换的笔记软件吗",
      "path": "pages/500 - ARCHIVE/已发布文章/obsidian 是可以用一辈子不换的笔记软件吗.md"
    },
    {
      "basename": "HOMEPAGE",
      "path": "HOMEPAGE.md"
    },
    {
      "basename": "个人努力与社会进程",
      "path": "pages/400 - RESOURCE/原子知识库/思维工具库/个人努力与社会进程.md"
    },
    {
      "basename": "dataview",
      "path": "pages/300 - AREA/知识管理/obsidian学习笔记/dataview.md"
    },
    {
      "basename": "LATEST",
      "path": "pages/LATEST.md"
    },
    {
      "basename": "做为甲方，如何管理外包项目",
      "path": "pages/000 - INBOX/做为甲方，如何管理外包项目.md"
    },
    {
      "basename": "反间计",
      "path": "pages/000 - INBOX/反间计.md"
    },
    {
      "basename": "unlinked files output",
      "path": "unlinked files output.md"
    },
    {
      "basename": "unresolved links output",
      "path": "unresolved links output.md"
    },
    {
      "basename": "SWOT",
      "path": "pages/400 - RESOURCE/原子知识库/方法库/SWOT.md"
    },
    {
      "basename": "工具理性与价值理性",
      "path": "pages/400 - RESOURCE/原子知识库/单词库&概念库/工具理性与价值理性.md"
    },
    {
      "basename": "软实力和硬通货",
      "path": "pages/400 - RESOURCE/人文社科通识/金融学/软实力和硬通货.md"
    },
    {
      "basename": "皮格马利翁效应",
      "path": "pages/400 - RESOURCE/人文社科通识/心理学/皮格马利翁效应.md"
    },
    {
      "basename": "渐进式 - progressive",
      "path": "pages/300 - AREA/知识管理/obsidian学习笔记/渐进式 - progressive.md"
    },
    {
      "basename": "text expand",
      "path": "pages/300 - AREA/知识管理/obsidian学习笔记/text expand.md"
    },
    {
      "basename": "obsidian的使用感受",
      "path": "pages/300 - AREA/知识管理/obsidian学习笔记/obsidian的使用感受.md"
    },
    {
      "basename": "obsidian入门",
      "path": "pages/300 - AREA/知识管理/obsidian学习笔记/obsidian入门.md"
    },
    {
      "basename": "dataview的数据来源",
      "path": "pages/300 - AREA/知识管理/obsidian学习笔记/dataview的数据来源.md"
    },
    {
      "basename": "anki",
      "path": "pages/300 - AREA/知识管理/obsidian学习笔记/anki.md"
    },
    {
      "basename": "notion",
      "path": "pages/300 - AREA/知识管理/notion学习笔记/notion.md"
    },
    {
      "basename": "思维导图",
      "path": "pages/300 - AREA/思维导图.md"
    },
    {
      "basename": "费曼技巧",
      "path": "pages/300 - AREA/人+科技融合/个人效率系统打造/费曼技巧.md"
    },
    {
      "basename": "obsidian插件",
      "path": "pages/300 - AREA/知识管理/obsidian学习笔记/obsidian插件.md"
    },
    {
      "basename": "MOCs",
      "path": "pages/MOCs.md"
    },
    {
      "basename": "TOCs",
      "path": "pages/TOCs.md"
    },
    {
      "basename": "个人知识管理",
      "path": "pages/300 - AREA/人+科技融合/个人效率系统打造/个人知识管理.md"
    },
    {
      "basename": "必备软件",
      "path": "pages/300 - AREA/人+科技融合/必备软件/必备软件.md"
    },
    {
      "basename": "PARA和MOC联用组织笔记",
      "path": "pages/300 - AREA/知识管理/obsidian学习笔记/PARA和MOC联用组织笔记.md"
    },
    {
      "basename": "以每日日志为入口",
      "path": "pages/000 - INBOX/以每日日志为入口.md"
    },
    {
      "basename": "工作和生活的效率体系建设",
      "path": "pages/300 - AREA/人+科技融合/工作和生活的效率体系建设.md"
    },
    {
      "basename": "个人知识笔记系统",
      "path": "pages/300 - AREA/人+科技融合/个人知识笔记系统.md"
    },
    {
      "basename": "MOC",
      "path": "pages/000 - INBOX/MOC.md"
    },
    {
      "basename": "云计算与个人",
      "path": "pages/200 - PROJECT/云计算与云原生/云计算与个人.md"
    },
    {
      "basename": "个人职业生涯",
      "path": "pages/200 - PROJECT/个人职业生涯/个人职业生涯.md"
    },
    {
      "basename": "云计算与云原生",
      "path": "pages/200 - PROJECT/云计算与云原生/云计算与云原生.md"
    },
    {
      "basename": "vscode必备插件",
      "path": "pages/200 - PROJECT/我的开源项目/vscode/vscode必备插件.md"
    }
  ],
  "omittedPaths": [
    "journals/"
  ],
  "maxLength": null
}